setup.cfg
setup.py
dekoruma_indexer/__init__.py
dekoruma_indexer/base_indexer.py
dekoruma_indexer.egg-info/PKG-INFO
dekoruma_indexer.egg-info/SOURCES.txt
dekoruma_indexer.egg-info/dependency_links.txt
dekoruma_indexer.egg-info/requires.txt
dekoruma_indexer.egg-info/top_level.txt