Metadata-Version: 1.0
Name: dekoruma-indexer
Version: 0.1.1
Summary: A package for indexer algolia
Home-page: https://github.com/jekidekoruma/indexer
Author: Dekoruma
Author-email: hello@dekoruma.com
License: UNKNOWN
Platform: UNKNOWN
